README.md
setup.cfg
setup.py
xgu/add_and_commit_changes.py
xgu/f_added.py
xgu/f_deleted.py
xgu/f_generic.py
xgu/f_modified.py
xgu/git_pull.py
xgu/git_status.py
xgu/guarantee_k_in_d.py
xgu/main.py
xgu/populate_changes_dict.py
xgu/prepare_q.py
xgu.egg-info/PKG-INFO
xgu.egg-info/SOURCES.txt
xgu.egg-info/dependency_links.txt
xgu.egg-info/top_level.txt
xgu/other/patch/do.py