Metadata-Version: 2.1
Name: xgu
Version: 0.0.8
Summary: Semi-Automatic Git Tool
Home-page: https://github.com/JohnForbes/xgu
Author: @JohnRForbes
Author-email: john.robert.forbes@gmail.com
License: MIT
Keywords: git
Platform: UNKNOWN
Classifier: Programming Language :: Python :: 3
Classifier: License :: OSI Approved :: MIT License
Classifier: Operating System :: OS Independent
Requires-Python: >=3.8
